encrust/__init__.py
encrust/_architecture.py
encrust/_build.py
encrust/_dosetup.py
encrust/_signing.py
encrust/_spawnutil.py
encrust/_type.py
encrust/_zip.py
encrust/api.py
encrust/cli.py
encrust/py.typed
encrust/required-python-entitlements.plist
encrust-2025.4.4.2.dist-info/licenses/LICENSE
encrust-2025.4.4.2.dist-info/METADATA
encrust-2025.4.4.2.dist-info/WHEEL
encrust-2025.4.4.2.dist-info/entry_points.txt
encrust-2025.4.4.2.dist-info/top_level.txt
encrust-2025.4.4.2.dist-info/RECORD
