Metadata-Version: 2.4
Name: encrust
Version: 2025.4.4.2
Summary: Sign, notarize, staple and archive Python mac apps.
Project-URL: Homepage, https://github.com/glyph/Encrust
License-File: LICENSE
Requires-Dist: twisted
Requires-Dist: click
Requires-Dist: delocate>=0.12.0
Requires-Dist: py2app
Requires-Dist: wheel_filename
Provides-Extra: mypy
Requires-Dist: mypy; extra == "mypy"
Requires-Dist: mypy-zope; extra == "mypy"
Dynamic: license-file
